{"name":"React-markdown-editor","tagline":"A markdown editor using React/Reflux","body":"# react-markdown-editor\r\nA markdown editor using React/Reflux.\r\n\r\n[![Build Status](http://img.shields.io/travis/jrm2k6/react-markdown-editor/master.svg?style=flat-square)](https://travis-ci.org/jrm2k6/react-markdown-editor)\r\n[![License](https://img.shields.io/npm/l/express.svg?style=flat-square)](http://www.opensource.org/licenses/MIT)\r\n[![Latest Version](https://img.shields.io/npm/v/npm.svg?style=flat-square)](https://www.npmjs.com/package/react-markdown-editor)\r\n[![Total Downloads](https://img.shields.io/npm/dm/localeval.svg?style=flat-square)](https://www.npmjs.com/package/react-markdown-editor)\r\n\r\n## Installation\r\n``` npm install --save react-markdown-editor ```\r\n\r\n## Features\r\nFrom the UI:\r\n\r\n- Bold\r\n- Italic\r\n- Header\r\n- Subheader\r\n- Link\r\n- Unordered List\r\n- Inline Images\r\n\r\nOf course it is a regular markdown editor (using the nice [markdown-js](https://github.com/evilstreak/markdown-js) library), so you are not limited to the UI. \r\n\r\n## Usage\r\nTo render the component:\r\n```\r\nvar React = require('react');\r\nvar MarkdownEditor = require('react-markdown-editor').MarkdownEditor;\r\n\r\nvar TestComponent = React.createClass({\r\n\trender: function() {\r\n\t\treturn (\r\n\t\t\t<MarkdownEditor initialContent=\"Test\"/>\r\n\t\t);\r\n\t}\r\n});\r\n\r\nReact.render(<TestComponent />, document.getElementById('content'));\r\n```\r\n\r\n```<MarkdownEditor /> ``` has only one prop, the initial content of the textarea.\r\n\r\nYou can also listen to content changes on the editor. If you are using Reflux, by listening to the changes on ```MarkdownEditorContentStore```.\r\nTo be able to do so, just ```require('react-markdown-editor').MarkdownEditorContentStore;```\r\n## Dependencies\r\nYou can modify the styles directly by modifying the styles declared in ```dist/MarkdownEditor.js```. The pre-existing styles assume that you are using Bootstrap and Font Awesome.\r\n## TODO\r\n- [x] Cross-browsers issues\r\n- [ ] Better solution for styles\r\n- [ ] Upgrade to React 0.13\r\n- [x] Unit testing\r\n- [ ] Cross-browsers testing\r\n\r\n## Issues/Contribution\r\nYou can open an issue on the github repo, or contact me directly by email.\r\n\r\n## Screenshots\r\n![Editing tab](http://i.imgur.com/XPdJmqm.png \"Editing tab\")\r\n![Preview tab](http://i.imgur.com/uavBSUN.png \"Preview tab\")\r\n","google":"","note":"Don't delete this file! It's used internally to help with page regeneration."}